{
    "data": {
        "allQuestionsCount": [
            {
                "difficulty": "All",
                "count": 3822
            },
            {
                "difficulty": "Easy",
                "count": 922
            },
            {
                "difficulty": "Medium",
                "count": 1997
            },
            {
                "difficulty": "Hard",
                "count": 903
            }
        ],
        "userContestRanking": {
            "attendedContestsCount": 26,
            "rating": 1911.267,
            "globalRanking": 31904,
            "totalParticipants": 818912,
            "topPercentage": 4.04,
            "badge": {
                "name": "Knight"
            }
        },
        "matchedUser": {
            "username": "icode100",
            "submitStats": {
                "acSubmissionNum": [
                    {
                        "difficulty": "All",
                        "count": 800,
                        "submissions": 1868
                    },
                    {
                        "difficulty": "Easy",
                        "count": 145,
                        "submissions": 248
                    },
                    {
                        "difficulty": "Medium",
                        "count": 525,
                        "submissions": 1309
                    },
                    {
                        "difficulty": "Hard",
                        "count": 130,
                        "submissions": 311
                    }
                ]
            }
        }
    }
}