{
    "data": {
        "allQuestionsCount": [
            {
                "difficulty": "All",
                "count": 3246
            },
            {
                "difficulty": "Easy",
                "count": 817
            },
            {
                "difficulty": "Medium",
                "count": 1703
            },
            {
                "difficulty": "Hard",
                "count": 726
            }
        ],
        "userContestRanking": {
            "attendedContestsCount": 16,
            "rating": 1626.379454971943,
            "globalRanking": 108019,
            "totalParticipants": 573899,
            "topPercentage": 19.28,
            "badge": null
        },
        "matchedUser": {
            "username": "icode100",
            "submitStats": {
                "acSubmissionNum": [
                    {
                        "difficulty": "All",
                        "count": 521,
                        "submissions": 829
                    },
                    {
                        "difficulty": "Easy",
                        "count": 95,
                        "submissions": 127
                    },
                    {
                        "difficulty": "Medium",
                        "count": 355,
                        "submissions": 591
                    },
                    {
                        "difficulty": "Hard",
                        "count": 71,
                        "submissions": 111
                    }
                ]
            }
        }
    }
}